ethicalgardeners/__init__.py
ethicalgardeners/action.py
ethicalgardeners/actionhandler.py
ethicalgardeners/agent.py
ethicalgardeners/algorithms.py
ethicalgardeners/constants.py
ethicalgardeners/gardenersenv.py
ethicalgardeners/gridworld.py
ethicalgardeners/main.py
ethicalgardeners/metricscollector.py
ethicalgardeners/observation.py
ethicalgardeners/renderer.py
ethicalgardeners/rewardfunctions.py
ethicalgardeners/configs/README.md
ethicalgardeners/configs/config.yaml
ethicalgardeners/configs/grid/from_code.yaml
ethicalgardeners/configs/grid/from_file.yaml
ethicalgardeners/configs/grid/random.yaml
ethicalgardeners/configs/metrics/export.yaml
ethicalgardeners/configs/metrics/full.yaml
ethicalgardeners/configs/metrics/none.yaml
ethicalgardeners/configs/metrics/send.yaml
ethicalgardeners/configs/observation/partial.yaml
ethicalgardeners/configs/observation/total.yaml
ethicalgardeners/configs/renderer/console.yaml
ethicalgardeners/configs/renderer/full.yaml
ethicalgardeners/configs/renderer/graphical.yaml
ethicalgardeners/configs/renderer/none.yaml
ethical_gardeners-0.0.1.dist-info/METADATA
ethical_gardeners-0.0.1.dist-info/WHEEL
ethical_gardeners-0.0.1.dist-info/RECORD
