Metadata-Version: 2.4
Name: ethical-gardeners
Version: 0.0.1
Summary: A RL environment for learning ethically-aligned behaviours
Project-URL: Source code, https://github.com/ethicsai/ethicalgardeners
Project-URL: Bug Tracker, https://github.com/ethicsai/ethicalgardeners/issues
Project-URL: Documentation, https://ethicsai.github.io/ethical-gardeners/
Author: Enzo Dos Anjos
Author-email: Rémy Chaput <rchaput.pro@gmail.com>
License-Expression: MIT
Keywords: Gym,Gymnasium,Machine Ethics,Multi-Agent System,OpenAI Gym,Reinforcement Learning
Classifier: Development Status :: 3 - Alpha
Classifier: Intended Audience :: Science/Research
Classifier: License :: OSI Approved :: MIT License
Classifier: Operating System :: OS Independent
Classifier: Programming Language :: Python :: 3
Classifier: Programming Language :: Python :: 3.9
Classifier: Programming Language :: Python :: 3.10
Classifier: Programming Language :: Python :: 3.11
Classifier: Programming Language :: Python :: 3.12
Classifier: Programming Language :: Python :: 3.13
Classifier: Topic :: Scientific/Engineering :: Artificial Intelligence
Requires-Python: >=3.9
Requires-Dist: gymnasium>=0.26.0
Requires-Dist: hydra-core>=1.2.0
Requires-Dist: numpy>=1.20.0
Requires-Dist: pettingzoo>=1.20.0
Provides-Extra: algorithms
Requires-Dist: sb3-contrib>=2.0.0; extra == 'algorithms'
Requires-Dist: stable-baselines3>=2.0.0; extra == 'algorithms'
Provides-Extra: dev
Requires-Dist: flake8>=4.0.0; extra == 'dev'
Requires-Dist: pytest>=7.0.0; extra == 'dev'
Provides-Extra: docs
Requires-Dist: furo>=2022.11.15; extra == 'docs'
Requires-Dist: sphinx-copybutton>=0.5.0; extra == 'docs'
Requires-Dist: sphinx-multiversion>=0.2.4; extra == 'docs'
Requires-Dist: sphinx>=5.0.0; extra == 'docs'
Provides-Extra: metrics
Requires-Dist: wandb>=0.12.0; extra == 'metrics'
Provides-Extra: viz
Requires-Dist: opencv-python>=4.5.0; extra == 'viz'
Requires-Dist: pygame>=2.0.0; extra == 'viz'
